qa_automation2/__init__.py
qa_automation2/adbcore.py
qa_automation2/loginfor.py
qa_automation2/qa_infor.py
qa_automation2/qautomationcore.py
qa_automation2-0.1.7.dist-info/METADATA
qa_automation2-0.1.7.dist-info/WHEEL
qa_automation2-0.1.7.dist-info/top_level.txt
qa_automation2-0.1.7.dist-info/RECORD
