Metadata-Version: 2.4
Name: qa_automation2
Version: 0.1.7
Summary: Automation test for phone
Author-email: Thoang <nhothoang@gmail.com>
License: GPL-3.0-only
Project-URL: Documentation, https://github.com/NhoThoang/QA_Automation2.git/README.md
Project-URL: Source, https://github.com/NhoThoang/QA_Automation2.git
Project-URL: Tracker, https://github.com/NhoThoang/QA_Automation2.git/issues
Requires-Dist: uiautomator2>=3.2.8
Requires-Dist: adbutils
